{
  "info": {}, 
  "filters": [
    {
      "parameters": [
        {
          "type": "CIAttributeTypePosition3", 
          "val": [
            0.0, 
            1.33, 
            1.0
          ], 
          "key": "inputRedShift"
        }, 
        {
          "type": "CIAttributeTypePosition3", 
          "val": [
            0.0, 
            1.19, 
            1.0
          ], 
          "key": "inputOrangeShift"
        }, 
        {
          "type": "CIAttributeTypePosition3", 
          "val": [
            0.0, 
            1.73, 
            1.0
          ], 
          "key": "inputYellowShift"
        }, 
        {
          "type": "CIAttributeTypePosition3", 
          "val": [
            0.0, 
            0.85, 
            1.0
          ], 
          "key": "inputGreenShift"
        }, 
        {
          "type": "CIAttributeTypePosition3", 
          "val": [
            0.0, 
            1.13, 
            1.0
          ], 
          "key": "inputAquaShift"
        }, 
        {
          "type": "CIAttributeTypePosition3", 
          "val": [
            0.0, 
            0.88, 
            1.0
          ], 
          "key": "inputBlueShift"
        }, 
        {
          "type": "CIAttributeTypePosition3", 
          "val": [
            0.0, 
            1.25, 
            1.0
          ], 
          "key": "inputPurpleShift"
        }, 
        {
          "type": "CIAttributeTypePosition3", 
          "val": [
            0.0, 
            1.09, 
            1.0
          ], 
          "key": "inputMagentaShift"
        }
      ], 
      "key": "MultiBandHSV"
    }, 
    {
      "parameters": [
        {
          "type": "CIAttributeTypeScalar", 
          "val": 0.001, 
          "key": "inputSaturation"
        }
      ], 
      "key": "SaturationFilter"
    }
  ], 
  "key": "../phixer/Config/Presets//Mastin Labs Ilford BW Pack - Nikon/3c.YellowFilter-N.json"
}