{
  "info": {
    "group": "", 
    "name": "LR-CrossProcess-03"
  }, 
  "filters": [
    {
      "parameters": [
        {
          "type": "CIAttributeTypeScalar", 
          "val": 0.2, 
          "key": "inputClarity"
        }
      ], 
      "key": "ClarityFilter"
    }, 
    {
      "parameters": [
        {
          "type": "CIAttributeTypeScalar", 
          "val": 0.9, 
          "key": "inputSaturation"
        }
      ], 
      "key": "SaturationFilter"
    }, 
    {
      "parameters": [
        {
          "type": "CIAttributeTypeScalar", 
          "val": 0.5, 
          "key": "inputSharpness"
        }
      ], 
      "key": "CISharpenLuminance"
    }, 
    {
      "parameters": [
        {
          "type": "CIAttributeTypeScalar", 
          "val": 0.025, 
          "key": "inputNoiseLevel"
        }, 
        {
          "type": "CIAttributeTypeScalar", 
          "val": 0.1, 
          "key": "inputSharpness"
        }
      ], 
      "key": "CINoiseReduction"
    }, 
    {
      "parameters": [
        {
          "type": "CIAttributeTypeVector", 
          "val": [
            0.0, 
            0.25, 
            0.5, 
            0.75, 
            1.0
          ], 
          "key": "inputRedXvalues"
        }, 
        {
          "type": "CIAttributeTypeVector", 
          "val": [
            0.0, 
            0.16758329685961265, 
            0.46600558047926466, 
            0.7814250738592843, 
            1.0
          ], 
          "key": "inputRedYvalues"
        }, 
        {
          "type": "CIAttributeTypeVector", 
          "val": [
            0.0, 
            0.25, 
            0.5, 
            0.75, 
            1.0
          ], 
          "key": "inputGreenXvalues"
        }, 
        {
          "type": "CIAttributeTypeVector", 
          "val": [
            0.0, 
            0.2970595472440945, 
            0.5627460629921259, 
            0.7970595472440944, 
            1.0
          ], 
          "key": "inputGreenYvalues"
        }, 
        {
          "type": "CIAttributeTypeVector", 
          "val": [
            0.0, 
            0.25, 
            0.5, 
            0.75, 
            1.0
          ], 
          "key": "inputBlueXvalues"
        }, 
        {
          "type": "CIAttributeTypeVector", 
          "val": [
            0.13333333333333333, 
            0.40046113956342216, 
            0.553315845944945, 
            0.6824538058245836, 
            0.8784313725490196
          ], 
          "key": "inputBlueYvalues"
        }
      ], 
      "key": "RGBChannelToneCurve"
    }, 
    {
      "parameters": [
        {
          "type": "CIAttributeTypeOffset", 
          "val": [
            0.0, 
            0.0
          ], 
          "key": "inputPoint0"
        }, 
        {
          "type": "CIAttributeTypeOffset", 
          "val": [
            0.25, 
            0.25
          ], 
          "key": "inputPoint1"
        }, 
        {
          "type": "CIAttributeTypeOffset", 
          "val": [
            0.5, 
            0.5
          ], 
          "key": "inputPoint2"
        }, 
        {
          "type": "CIAttributeTypeOffset", 
          "val": [
            0.75, 
            0.75
          ], 
          "key": "inputPoint3"
        }, 
        {
          "type": "CIAttributeTypeOffset", 
          "val": [
            1.0, 
            1.0
          ], 
          "key": "inputPoint4"
        }
      ], 
      "key": "CIToneCurve"
    }
  ], 
  "key": "../phixer/Config/Presets//Lightroom/LR-CrossProcess-03.json"
}