{
  "info": {
    "group": "N Polaroid Film Stocks", 
    "name": "N - Polaroid 690"
  }, 
  "filters": [
    {
      "parameters": [
        {
          "type": "CIAttributeTypeScalar", 
          "val": -0.1, 
          "key": "inputClarity"
        }
      ], 
      "key": "ClarityFilter"
    }, 
    {
      "parameters": [
        {
          "type": "CIAttributeTypeScalar", 
          "val": 0.95, 
          "key": "inputSaturation"
        }
      ], 
      "key": "SaturationFilter"
    }, 
    {
      "parameters": [
        {
          "type": "CIAttributeTypeScalar", 
          "val": 0.025, 
          "key": "inputNoiseLevel"
        }, 
        {
          "type": "CIAttributeTypeScalar", 
          "val": 0.1, 
          "key": "inputSharpness"
        }
      ], 
      "key": "CINoiseReduction"
    }, 
    {
      "parameters": [
        {
          "type": "CIAttributeTypeScalar", 
          "val": 0.1, 
          "key": "inputAmount"
        }, 
        {
          "type": "CIAttributeTypeScalar", 
          "val": 0.6, 
          "key": "inputSize"
        }
      ], 
      "key": "FilmGrainFilter"
    }, 
    {
      "parameters": [
        {
          "type": "CIAttributeTypeScalar", 
          "val": 0.15, 
          "key": "inputShadowAmount"
        }, 
        {
          "type": "CIAttributeTypeScalar", 
          "val": 0.9, 
          "key": "inputHighlightAmount"
        }
      ], 
      "key": "CIHighlightShadowAdjust"
    }, 
    {
      "parameters": [
        {
          "type": "CIAttributeTypeVector", 
          "val": [
            0.0, 
            0.25, 
            0.5, 
            0.75, 
            1.0
          ], 
          "key": "inputRedXvalues"
        }, 
        {
          "type": "CIAttributeTypeVector", 
          "val": [
            0.0, 
            0.2636450079917015, 
            0.521487246036256, 
            0.7918893157380296, 
            0.9803921568627451
          ], 
          "key": "inputRedYvalues"
        }, 
        {
          "type": "CIAttributeTypeVector", 
          "val": [
            0.0, 
            0.25, 
            0.5, 
            0.75, 
            1.0
          ], 
          "key": "inputGreenXvalues"
        }, 
        {
          "type": "CIAttributeTypeVector", 
          "val": [
            0.0, 
            0.22067588307146424, 
            0.5327467015140366, 
            0.8044099056026474, 
            1.0
          ], 
          "key": "inputGreenYvalues"
        }, 
        {
          "type": "CIAttributeTypeVector", 
          "val": [
            0.0, 
            0.25, 
            0.5, 
            0.75, 
            1.0
          ], 
          "key": "inputBlueXvalues"
        }, 
        {
          "type": "CIAttributeTypeVector", 
          "val": [
            0.0, 
            0.1411764705882353, 
            0.49019607843137253, 
            0.8627450980392157, 
            1.0
          ], 
          "key": "inputBlueYvalues"
        }
      ], 
      "key": "RGBChannelToneCurve"
    }, 
    {
      "parameters": [
        {
          "type": "CIAttributeTypePosition3", 
          "val": [
            0.0125, 
            1.0, 
            0.65
          ], 
          "key": "inputRedShift"
        }, 
        {
          "type": "CIAttributeTypePosition3", 
          "val": [
            0.0, 
            0.95, 
            1.0
          ], 
          "key": "inputOrangeShift"
        }, 
        {
          "type": "CIAttributeTypePosition3", 
          "val": [
            0.0, 
            1.05, 
            0.9
          ], 
          "key": "inputYellowShift"
        }, 
        {
          "type": "CIAttributeTypePosition3", 
          "val": [
            -0.025, 
            0.9, 
            0.75
          ], 
          "key": "inputGreenShift"
        }, 
        {
          "type": "CIAttributeTypePosition3", 
          "val": [
            0.0, 
            0.75, 
            0.95
          ], 
          "key": "inputAquaShift"
        }, 
        {
          "type": "CIAttributeTypePosition3", 
          "val": [
            -0.00625, 
            0.8, 
            0.75
          ], 
          "key": "inputBlueShift"
        }, 
        {
          "type": "CIAttributeTypePosition3", 
          "val": [
            0.0, 
            0.85, 
            1.0
          ], 
          "key": "inputPurpleShift"
        }, 
        {
          "type": "CIAttributeTypePosition3", 
          "val": [
            0.0, 
            0.8, 
            0.9
          ], 
          "key": "inputMagentaShift"
        }
      ], 
      "key": "MultiBandHSV"
    }, 
    {
      "parameters": [
        {
          "type": "CIAttributeTypeOffset", 
          "val": [
            0.0, 
            0.1607843137254903
          ], 
          "key": "inputPoint0"
        }, 
        {
          "type": "CIAttributeTypeOffset", 
          "val": [
            0.15, 
            0.29007224197780174
          ], 
          "key": "inputPoint1"
        }, 
        {
          "type": "CIAttributeTypeOffset", 
          "val": [
            0.6, 
            0.5019293733012774
          ], 
          "key": "inputPoint2"
        }, 
        {
          "type": "CIAttributeTypeOffset", 
          "val": [
            0.75, 
            0.6972049160533496
          ], 
          "key": "inputPoint3"
        }, 
        {
          "type": "CIAttributeTypeOffset", 
          "val": [
            1.0, 
            1.0
          ], 
          "key": "inputPoint4"
        }
      ], 
      "key": "CIToneCurve"
    }
  ], 
  "key": "../phixer/Config/Presets//AnalogFilm/N-Polaroid690.json"
}
